{"id":"te_87510289-3a11-4bed-afc8-06e4a6a92dd6","type":"CLI_USER","properties":{"with_id":false},"timestamp":"2026-05-01T21:53:35.097Z","machine_id":"5f866682-78f2-41ca-a3d2-82146da13787","os_info":{"node_version":"v24.14.0","platform":"win32","release":"10.0.26200","cpus":"Intel(R) Core(TM) Ultra 7 255HX","is_ci":false,"ci_name":null,"arch":"x64","docker":false},"medusa_version":"2.14.2","cli_version":"2.14.2","feature_flags":[],"modules":[],"plugins":[]}
{"id":"te_e89e8390-e429-4696-98ef-a8d757381ac3","type":"CLI_USER_COMPLETED","properties":{"with_id":false},"timestamp":"2026-05-01T21:53:39.173Z","machine_id":"5f866682-78f2-41ca-a3d2-82146da13787","os_info":{"node_version":"v24.14.0","platform":"win32","release":"10.0.26200","cpus":"Intel(R) Core(TM) Ultra 7 255HX","is_ci":false,"ci_name":null,"arch":"x64","docker":false},"medusa_version":"2.14.2","cli_version":"2.14.2","feature_flags":[],"modules":[],"plugins":[]}
{"id":"te_19f89710-0078-41cf-9fad-4b1811f7a1c1","type":"CLI_START","properties":{},"timestamp":"2026-05-01T21:54:07.859Z","machine_id":"5f866682-78f2-41ca-a3d2-82146da13787","os_info":{"node_version":"v24.14.0","platform":"win32","release":"10.0.26200","cpus":"Intel(R) Core(TM) Ultra 7 255HX","is_ci":false,"ci_name":null,"arch":"x64","docker":false},"medusa_version":"2.14.2","cli_version":"2.14.2","feature_flags":[],"modules":[],"plugins":[]}
{"id":"te_0a7de63d-7020-4ce4-862a-6070695f9b78","type":"CLI_START_COMPLETED","properties":{},"timestamp":"2026-05-01T21:54:21.438Z","machine_id":"5f866682-78f2-41ca-a3d2-82146da13787","os_info":{"node_version":"v24.14.0","platform":"win32","release":"10.0.26200","cpus":"Intel(R) Core(TM) Ultra 7 255HX","is_ci":false,"ci_name":null,"arch":"x64","docker":false},"medusa_version":"2.14.2","cli_version":"2.14.2","feature_flags":[],"modules":[],"plugins":[]}
{"id":"te_e37de6c5-aa87-4fa3-8ea7-55461ef03a4d","type":"PING","properties":{},"timestamp":"2026-05-02T00:00:00.027Z","machine_id":"5f866682-78f2-41ca-a3d2-82146da13787","os_info":{"node_version":"v24.14.0","platform":"win32","release":"10.0.26200","cpus":"Intel(R) Core(TM) Ultra 7 255HX","is_ci":false,"ci_name":null,"arch":"x64","docker":false},"medusa_version":"2.14.2","cli_version":"2.14.2","feature_flags":[],"modules":[],"plugins":[]}
